[{"ID":1000,"Name":"<color=#66463e>Cat</c>"},{"ID":1001,"Name":"<color=#66463e>Dog</c>"},{"ID":1002,"Name":"<color=#66463e>Bird</c>"},{"ID":1003,"Name":"<color=#66463e>Pig</c>"},{"ID":1004,"Name":"<color=#66463e>Fish</c>"},{"ID":1005,"Name":"<color=#66463e>Tortoise</c>"},{"ID":1006,"Name":"<color=#66463e>Rabbit</c>"},{"ID":1007,"Name":"<color=#66463e>Sheep</c>"},{"ID":1008,"Name":"<color=#66463e>Horse</c>"},{"ID":1009,"Name":"<color=#66463e>Snake</c>"},{"ID":1010,"Name":"<color=#66463e>Chicken</c>"},{"ID":1011,"Name":"<color=#66463e>Duck</c>"},{"ID":1012,"Name":"<color=#66463e>Frog</c>"},{"ID":1013,"Name":"<color=#66463e>Fox</c>"},{"ID":1014,"Name":"<color=#66463e>Rat</c>"}]